Cryptix/__init__.py
Cryptix/cryptix.py
Cryptix-0.1.1.dist-info/LICENSE
Cryptix-0.1.1.dist-info/METADATA
Cryptix-0.1.1.dist-info/WHEEL
Cryptix-0.1.1.dist-info/top_level.txt
Cryptix-0.1.1.dist-info/RECORD
