Metadata-Version: 2.1
Name: Cryptix
Version: 0.1.1
Summary: A versatile cryptography library for various encryption and decryption techniques.
Home-page: https://github.com/president-xd/Cryptix
Author: Mohsin Mukhtiar Lashari Baloch
Author-email: lasharimohsin19@gmail.com
Classifier: Programming Language :: Python :: 3
Classifier: License :: OSI Approved :: MIT License
Classifier: Operating System :: OS Independent
Classifier: Development Status :: 3 - Alpha
Classifier: Intended Audience :: Developers
Classifier: Topic :: Security :: Cryptography
Requires-Python: >=3.6
License-File: LICENSE
Requires-Dist: cryptography
Requires-Dist: numpy
